swagccg/__init__.py
swagccg/__main__.py
swagccg/client/__init__.py
swagccg/example/__init__.py
swagccg/example/auto_client.py
swagccg/src/__init__.py
swagccg/src/client_template.py
swagccg/src/make_client.py
swagccg-0.4.0.dist-info/LICENSE
swagccg-0.4.0.dist-info/METADATA
swagccg-0.4.0.dist-info/WHEEL
swagccg-0.4.0.dist-info/top_level.txt
swagccg-0.4.0.dist-info/RECORD
