Metadata-Version: 2.1
Name: swagccg
Version: 0.4.0
Summary: Swagger Client Code Generator. Using Python. For Python.
Home-page: https://github.com/erkandem/swagccg-py2py
Author: Erkan Demiralay
Author-email: erkan.dem@pm.me
License: UNKNOWN
Project-URL: Bug Reports, https://github.com/erkandem/swagccg-py2py/issues
Project-URL: Source, https://github.com/erkandem/swagccg-py2py/
Project-URL: Documentation, https://erkandem.github.io/swagccg-py2py/
Keywords: REST api-client client-code code-generator swagger openapi
Platform: UNKNOWN
Classifier: Development Status :: 3 - Alpha
Classifier: Intended Audience :: Developers
Classifier: Topic :: Software Development :: Build Tools
Classifier: License :: OSI Approved :: MIT License
Classifier: Programming Language :: Python :: 3.6
Classifier: Programming Language :: Python :: 3.7
Classifier: Programming Language :: Python :: 3.8
